<?xml version="1.0"?>
<cena version="0.5.2"><result judgetime="40818.7314384375"><problem title="DerProze" filename="DerProze.cpp" status="1" hash="2978191651"><testcase status="7" exitcode="0" detail="" time="0.01" memory="576" score="5"/><testcase status="7" exitcode="0" detail="" time="0.01" memory="576" score="5"/><testcase status="7" exitcode="0" detail="" time="0.01" memory="576" score="5"/><testcase status="7" exitcode="0" detail="" time="0.01" memory="576" score="5"/><testcase status="7" exitcode="0" detail="" time="0.01" memory="576" score="5"/><testcase status="7" exitcode="0" detail="" time="0.01" memory="576" score="5"/><testcase status="7" exitcode="0" detail="" time="0.01" memory="576" score="5"/><testcase status="7" exitcode="0" detail="" time="0.01" memory="576" score="5"/><testcase status="7" exitcode="0" detail="" time="0.01" memory="576" score="5"/><testcase status="7" exitcode="0" detail="" time="0.01" memory="576" score="5"/><testcase status="7" exitcode="0" detail="" time="0.01" memory="576" score="5"/><testcase status="7" exitcode="0" detail="" time="0.01" memory="576" score="5"/><testcase status="7" exitcode="0" detail="" time="0.01" memory="576" score="5"/><testcase status="7" exitcode="0" detail="" time="0.01" memory="576" score="5"/><testcase status="7" exitcode="0" detail="" time="0.01" memory="576" score="5"/><testcase status="7" exitcode="0" detail="" time="0.01" memory="576" score="5"/><testcase status="7" exitcode="0" detail="" time="0.01" memory="576" score="5"/><testcase status="7" exitcode="0" detail="" time="0.01" memory="576" score="5"/><testcase status="7" exitcode="0" detail="" time="0.01" memory="576" score="5"/><testcase status="7" exitcode="0" detail="" time="0.01" memory="576" score="5"/></problem><problem title="Castle" filename="Castle.cpp" status="1" hash="3790174563"><testcase status="7" exitcode="0" detail="" time="0.03" memory="9496" score="10"/><testcase status="7" exitcode="0" detail="" time="0.01" memory="9496" score="10"/><testcase status="7" exitcode="0" detail="" time="0.09" memory="9496" score="10"/><testcase status="7" exitcode="0" detail="" time="0.35" memory="9220" score="10"/><testcase status="7" exitcode="0" detail="" time="0.01" memory="9220" score="10"/><testcase status="7" exitcode="0" detail="" time="0.01" memory="9220" score="10"/><testcase status="7" exitcode="0" detail="" time="0.01" memory="9220" score="10"/><testcase status="7" exitcode="0" detail="" time="0.01" memory="9220" score="10"/><testcase status="7" exitcode="0" detail="" time="0.03" memory="9220" score="10"/><testcase status="7" exitcode="0" detail="" time="0.07" memory="9220" score="10"/></problem><problem title="Metamorphosis" filename="Metamorphosis.cpp" status="1" hash="2082125588"><testcase status="7" exitcode="0" detail="" time="0.01" memory="576" score="1"/><testcase status="7" exitcode="0" detail="" time="0.01" memory="576" score="1"/><testcase status="7" exitcode="0" detail="" time="0.01" memory="576" score="1"/><testcase status="7" exitcode="0" detail="" time="0.01" memory="576" score="1"/><testcase status="7" exitcode="0" detail="" time="0.01" memory="576" score="1"/><testcase status="7" exitcode="0" detail="" time="0.01" memory="576" score="1"/><testcase status="7" exitcode="0" detail="" time="0.01" memory="576" score="1"/><testcase status="7" exitcode="0" detail="" time="0.01" memory="576" score="1"/><testcase status="7" exitcode="0" detail="" time="0.03" memory="576" score="1"/><testcase status="7" exitcode="0" detail="" time="0.01" memory="576" score="1"/><testcase status="7" exitcode="0" detail="" time="0.01" memory="576" score="1"/><testcase status="7" exitcode="0" detail="" time="0.01" memory="576" score="1"/><testcase status="7" exitcode="0" detail="" time="0.01" memory="576" score="1"/><testcase status="7" exitcode="0" detail="" time="0.01" memory="576" score="1"/><testcase status="7" exitcode="0" detail="" time="0.01" memory="576" score="1"/><testcase status="7" exitcode="0" detail="" time="0.01" memory="576" score="1"/><testcase status="7" exitcode="0" detail="" time="0.01" memory="576" score="1"/><testcase status="7" exitcode="0" detail="" time="0.01" memory="576" score="1"/><testcase status="7" exitcode="0" detail="" time="0.01" memory="576" score="1"/><testcase status="7" exitcode="0" detail="" time="0.01" memory="576" score="1"/><testcase status="7" exitcode="0" detail="" time="0.01" memory="576" score="1"/><testcase status="7" exitcode="0" detail="" time="0.01" memory="576" score="1"/><testcase status="7" exitcode="0" detail="" time="0.01" memory="576" score="1"/><testcase status="7" exitcode="0" detail="" time="0.01" memory="576" score="1"/><testcase status="7" exitcode="0" detail="" time="0.01" memory="576" score="1"/><testcase status="7" exitcode="0" detail="" time="0.01" memory="576" score="1"/><testcase status="7" exitcode="0" detail="" time="0.01" memory="576" score="1"/><testcase status="7" exitcode="0" detail="" time="0.01" memory="576" score="1"/><testcase status="7" exitcode="0" detail="" time="0.01" memory="576" score="1"/><testcase status="7" exitcode="0" detail="" time="0.01" memory="576" score="1"/><testcase status="7" exitcode="0" detail="" time="0.01" memory="576" score="1"/><testcase status="7" exitcode="0" detail="" time="0.01" memory="576" score="1"/><testcase status="7" exitcode="0" detail="" time="0.01" memory="576" score="1"/><testcase status="7" exitcode="0" detail="" time="0.01" memory="576" score="1"/><testcase status="7" exitcode="0" detail="" time="0.01" memory="576" score="1"/><testcase status="7" exitcode="0" detail="" time="0.01" memory="576" score="1"/><testcase status="7" exitcode="0" detail="" time="0.01" memory="576" score="1"/><testcase status="7" exitcode="0" detail="" time="0.01" memory="576" score="1"/><testcase status="7" exitcode="0" detail="" time="0.01" memory="576" score="1"/><testcase status="7" exitcode="0" detail="" time="0.03" memory="576" score="1"/><testcase status="7" exitcode="0" detail="" time="0.01" memory="576" score="1"/><testcase status="7" exitcode="0" detail="" time="0.01" memory="576" score="1"/><testcase status="7" exitcode="0" detail="" time="0.01" memory="576" score="1"/><testcase status="7" exitcode="0" detail="" time="0.01" memory="576" score="1"/><testcase status="7" exitcode="0" detail="" time="0.01" memory="576" score="1"/><testcase status="7" exitcode="0" detail="" time="0.01" memory="576" score="1"/><testcase status="7" exitcode="0" detail="" time="0.01" memory="576" score="1"/><testcase status="7" exitcode="0" detail="" time="0.01" memory="576" score="1"/><testcase status="7" exitcode="0" detail="" time="0.01" memory="576" score="1"/><testcase status="7" exitcode="0" detail="" time="0.01" memory="576" score="1"/><testcase status="7" exitcode="0" detail="" time="0.01" memory="576" score="1"/><testcase status="7" exitcode="0" detail="" time="0.01" memory="576" score="1"/><testcase status="7" exitcode="0" detail="" time="0.01" memory="576" score="1"/><testcase status="7" exitcode="0" detail="" time="0.01" memory="576" score="1"/><testcase status="7" exitcode="0" detail="" time="0.01" memory="576" score="1"/><testcase status="7" exitcode="0" detail="" time="0.01" memory="576" score="1"/><testcase status="7" exitcode="0" detail="" time="0.01" memory="576" score="1"/><testcase status="7" exitcode="0" detail="" time="0.01" memory="576" score="1"/><testcase status="7" exitcode="0" detail="" time="0.01" memory="576" score="1"/><testcase status="7" exitcode="0" detail="" time="0.01" memory="576" score="1"/><testcase status="7" exitcode="0" detail="" time="0.01" memory="576" score="1"/><testcase status="7" exitcode="0" detail="" time="0.01" memory="576" score="1"/><testcase status="7" exitcode="0" detail="" time="0.01" memory="576" score="1"/><testcase status="7" exitcode="0" detail="" time="0.01" memory="576" score="1"/><testcase status="7" exitcode="0" detail="" time="0.01" memory="576" score="1"/><testcase status="7" exitcode="0" detail="" time="0.01" memory="576" score="1"/><testcase status="7" exitcode="0" detail="" time="0.01" memory="576" score="1"/><testcase status="7" exitcode="0" detail="" time="0.01" memory="576" score="1"/><testcase status="7" exitcode="0" detail="" time="0.01" memory="576" score="1"/><testcase status="7" exitcode="0" detail="" time="0.01" memory="576" score="1"/><testcase status="7" exitcode="0" detail="" time="0.01" memory="576" score="1"/><testcase status="7" exitcode="0" detail="" time="0.01" memory="576" score="1"/><testcase status="7" exitcode="0" detail="" time="0.01" memory="576" score="1"/><testcase status="7" exitcode="0" detail="" time="0.01" memory="576" score="1"/><testcase status="7" exitcode="0" detail="" time="0.01" memory="576" score="1"/><testcase status="7" exitcode="0" detail="" time="0.01" memory="576" score="1"/><testcase status="7" exitcode="0" detail="" time="0.01" memory="576" score="1"/><testcase status="7" exitcode="0" detail="" time="0.01" memory="576" score="1"/><testcase status="7" exitcode="0" detail="" time="0.03" memory="576" score="1"/><testcase status="7" exitcode="0" detail="" time="0.01" memory="576" score="1"/><testcase status="7" exitcode="0" detail="" time="0.01" memory="576" score="1"/><testcase status="7" exitcode="0" detail="" time="0.01" memory="576" score="1"/><testcase status="7" exitcode="0" detail="" time="0.01" memory="576" score="1"/><testcase status="7" exitcode="0" detail="" time="0.01" memory="576" score="1"/><testcase status="7" exitcode="0" detail="" time="0.01" memory="576" score="1"/><testcase status="7" exitcode="0" detail="" time="0.01" memory="576" score="1"/><testcase status="7" exitcode="0" detail="" time="0.01" memory="576" score="1"/><testcase status="7" exitcode="0" detail="" time="0.01" memory="576" score="1"/><testcase status="7" exitcode="0" detail="" time="0.01" memory="576" score="1"/><testcase status="7" exitcode="0" detail="" time="0.01" memory="576" score="1"/><testcase status="7" exitcode="0" detail="" time="0.03" memory="576" score="1"/><testcase status="7" exitcode="0" detail="" time="0.01" memory="576" score="1"/><testcase status="7" exitcode="0" detail="" time="0.01" memory="576" score="1"/><testcase status="7" exitcode="0" detail="" time="0.03" memory="576" score="1"/><testcase status="7" exitcode="0" detail="" time="0.01" memory="576" score="1"/><testcase status="7" exitcode="0" detail="" time="0.01" memory="576" score="1"/><testcase status="7" exitcode="0" detail="" time="0.01" memory="576" score="1"/><testcase status="7" exitcode="0" detail="" time="0.01" memory="576" score="1"/><testcase status="7" exitcode="0" detail="" time="0.01" memory="576" score="1"/><testcase status="7" exitcode="0" detail="" time="0.01" memory="576" score="1"/></problem></result></cena>
